ndbcrealtime/__init__.py
ndbcrealtime-0.0.4.dist-info/LICENSE
ndbcrealtime-0.0.4.dist-info/LICENSE.txt
ndbcrealtime-0.0.4.dist-info/METADATA
ndbcrealtime-0.0.4.dist-info/WHEEL
ndbcrealtime-0.0.4.dist-info/top_level.txt
ndbcrealtime-0.0.4.dist-info/RECORD
