Metadata-Version: 2.1
Name: ndbcrealtime
Version: 0.0.4
Summary: NDBC Real Time Buoy Observation Data Wrapper.
Home-page: https://github.com/djtimca/ndbc-api
Author: Tim Empringham
Author-email: tim.empringham@live.ca
License: apache-2.0
Download-URL: https://github.com/djtimca/ndbc-api/archive/refs/tags/0.0.4.tar.gz
Keywords: NDBC,Buoy,Waves,Wind,Weather
Platform: UNKNOWN
Classifier: Development Status :: 3 - Alpha
Classifier: Intended Audience :: Developers
Classifier: Topic :: Software Development :: Build Tools
Classifier: License :: OSI Approved :: Apache Software License
Classifier: Programming Language :: Python :: 3
Classifier: Programming Language :: Python :: 3.4
Classifier: Programming Language :: Python :: 3.5
Classifier: Programming Language :: Python :: 3.6
Requires-Python: >=3.8
License-File: LICENSE
License-File: LICENSE.txt
